docs/README.md
docs/__init__.py
docs/calibration-guide.md
docs/data-schema.md
docs/development-guide.md
docs/microscope-installation-guide.md
docs/napari-plugin-guide.md
docs/reconstruction-guide.md
docs/software-installation-guide.md
docs/images/HSV_legend.png
docs/images/JCh_Color_legend.png
docs/images/JCh_legend.png
docs/images/acq_finished.png
docs/images/acquire_buttons.png
docs/images/acquisition_settings.png
docs/images/advanced.png
docs/images/cap_bg.png
docs/images/cli_structure.png
docs/images/comms_video_screenshot.png
docs/images/connect_to_mm.png
docs/images/create_group.png
docs/images/create_group_voltage.png
docs/images/create_preset.png
docs/images/create_preset_voltage.png
docs/images/general_reconstruction_settings.png
docs/images/ideal_plot.png
docs/images/modulation.png
docs/images/no-overlay.png
docs/images/overlay-demo.png
docs/images/overlay.png
docs/images/phase_reconstruction_settings.png
docs/images/poincare_swing.svg
docs/images/recOrder_Fig1_Overview.png
docs/images/recOrder_plugin_logo.png
docs/images/run_calib.png
docs/images/run_port.png
recOrder/__init__.py
recOrder/_version.py
recOrder/napari.yaml
recOrder/acq/__init__.py
recOrder/acq/acq_functions.py
recOrder/acq/acquisition_workers.py
recOrder/calib/Calibration.py
recOrder/calib/Optimization.py
recOrder/calib/__init__.py
recOrder/calib/calibration_workers.py
recOrder/cli/apply_inverse_models.py
recOrder/cli/apply_inverse_transfer_function.py
recOrder/cli/compute_transfer_function.py
recOrder/cli/main.py
recOrder/cli/option_eat_all.py
recOrder/cli/parsing.py
recOrder/cli/printing.py
recOrder/cli/reconstruct.py
recOrder/cli/settings.py
recOrder/cli/utils.py
recOrder/io/__init__.py
recOrder/io/_reader.py
recOrder/io/core_functions.py
recOrder/io/metadata_reader.py
recOrder/io/utils.py
recOrder/plugin/__init__.py
recOrder/plugin/gui.py
recOrder/plugin/gui.ui
recOrder/plugin/main_widget.py
recOrder/scripts/__init__.py
recOrder/scripts/launch_napari.py
recOrder_napari-0.4.1.dist-info/LICENSE
recOrder_napari-0.4.1.dist-info/METADATA
recOrder_napari-0.4.1.dist-info/WHEEL
recOrder_napari-0.4.1.dist-info/entry_points.txt
recOrder_napari-0.4.1.dist-info/top_level.txt
recOrder_napari-0.4.1.dist-info/RECORD
