Metadata-Version: 2.1
Name: recOrder-napari
Version: 0.4.1
Summary: Computational microscopy toolkit for label-free imaging
Home-page: https://github.com/mehta-lab/recOrder
Author: Computational Microscopy Platform, CZ Biohub
Author-email: shalin.mehta@czbiohub.org
License: BSD 3-Clause License
Project-URL: Bug Tracker, https://github.com/mehta-lab/recOrder/issues
Project-URL: Documentation, https://github.com/mehta-lab/recOrder/wiki
Project-URL: Source Code, https://github.com/mehta-lab/recOrder/tree/main/recOrder
Project-URL: User Support, https://github.com/mehta-lab/recOrder/issues
Classifier: License :: OSI Approved :: BSD License
Classifier: Programming Language :: Python
Classifier: Programming Language :: Python :: 3 :: Only
Classifier: Programming Language :: Python :: 3.9
Classifier: Programming Language :: Python :: 3.10
Classifier: Topic :: Scientific/Engineering
Classifier: Topic :: Scientific/Engineering :: Visualization
Classifier: Topic :: Scientific/Engineering :: Information Analysis
Classifier: Topic :: Scientific/Engineering :: Bio-Informatics
Classifier: Topic :: Utilities
Classifier: Framework :: napari
Classifier: Operating System :: Microsoft :: Windows
Classifier: Operating System :: POSIX
Classifier: Operating System :: Unix
Classifier: Operating System :: MacOS
Requires-Python: >=3.9
License-File: LICENSE
Requires-Dist: waveorder ==2.0.0rc3
Requires-Dist: pycromanager ==0.27.2
Requires-Dist: click >=8.0.1
Requires-Dist: natsort >=7.1.1
Requires-Dist: colorspacious >=1.1.2
Requires-Dist: pyqtgraph >=0.12.3
Requires-Dist: napari-ome-zarr >=0.3.2
Requires-Dist: napari[pyqt6_experimental]
Requires-Dist: importlib-metadata
Requires-Dist: iohub ==0.1.0.dev5
Requires-Dist: wget >=3.2
Provides-Extra: dev
Requires-Dist: pytest >=5.0.0 ; extra == 'dev'
Requires-Dist: pytest-cov ; extra == 'dev'
Requires-Dist: pytest-qt ; extra == 'dev'
Requires-Dist: tox ; extra == 'dev'
Requires-Dist: pre-commit ; extra == 'dev'
Requires-Dist: black ; extra == 'dev'
Requires-Dist: hypothesis ; extra == 'dev'
